ecg_i2s/__init__.py
ecg_i2s/ecg.py
ecg_i2s/ecgnew.py
ecg_i2s-0.2.2.dist-info/METADATA
ecg_i2s-0.2.2.dist-info/WHEEL
ecg_i2s-0.2.2.dist-info/top_level.txt
ecg_i2s-0.2.2.dist-info/RECORD
