Metadata-Version: 2.1
Name: ecg_i2s
Version: 0.2.2
Summary: ecg_i2s123
Author: zou linzhuang
Author-email: xzxg001@gmail.com
License: MIT License
Classifier: Programming Language :: Python :: 3
Classifier: License :: OSI Approved :: MIT License
Classifier: Operating System :: OS Independent
